tuning_metrics/__init__.py
tuning_metrics/metrics.py
tuning_metrics/space.py
tuning_metrics/utils.py
tuning_metrics-0.1.2.dist-info/LICENSE
tuning_metrics-0.1.2.dist-info/METADATA
tuning_metrics-0.1.2.dist-info/WHEEL
tuning_metrics-0.1.2.dist-info/top_level.txt
tuning_metrics-0.1.2.dist-info/RECORD
